setup.py
luigi_slack/__init__.py
luigi_slack/api.py
luigi_slack/events.py
luigi_slack/slack_api.py
luigi_slack.egg-info/PKG-INFO
luigi_slack.egg-info/SOURCES.txt
luigi_slack.egg-info/dependency_links.txt
luigi_slack.egg-info/not-zip-safe
luigi_slack.egg-info/requires.txt
luigi_slack.egg-info/top_level.txt