Metadata-Version: 1.1
Name: luigi-slack
Version: 0.1.6
Summary: Send Slack notifications to report on Luigi pipelines
Home-page: https://github.com/bonzanini
Author: Marco Bonzanini
Author-email: marco.bonzanini@gmail.com
License: MIT
Platform: UNKNOWN
Classifier: Environment :: Console
Classifier: Intended Audience :: Developers
Classifier: Intended Audience :: System Administrators
Classifier: Operating System :: OS Independent
Classifier: Programming Language :: Python
Classifier: License :: OSI Approved :: MIT License
Classifier: Programming Language :: Python :: 3.4
Classifier: Topic :: System :: Monitoring
